LICENSE.txt
setup.py
SpaceXRMC.egg-info/PKG-INFO
SpaceXRMC.egg-info/SOURCES.txt
SpaceXRMC.egg-info/dependency_links.txt
SpaceXRMC.egg-info/top_level.txt
code/__init__.py
code/ramz.py