Metadata-Version: 2.1
Name: SpaceXRMC
Version: 0.3
Summary: python bbasic spacex
Author: Ramz Al
Classifier: Programming Language :: Python :: 3
Classifier: Operating System :: OS Independent
Classifier: License :: OSI Approved :: MIT License
License-File: LICENSE.txt
